[
  {
    "id": 1,
    "category": "skeleton",
    "question": "人体で最も大きい骨はどれ？",
    "choices": ["大腿骨", "脛骨", "腸骨", "上腕骨"],
    "answer": 0
  },
  {
    "id": 2,
    "category": "skeleton",
    "question": "人体で最も小さい骨はどれ？",
    "choices": ["耳小骨（アブミ骨）", "舟状骨", "豆状骨", "距骨"],
    "answer": 0
  },
  {
    "id": 3,
    "category": "skeleton",
    "question": "上腕骨頭がはまり込む骨の部位はどれ？",
    "choices": ["肩甲骨関節窩", "寛骨臼", "上腕骨小結節", "橈骨頭"],
    "answer": 0
  },
  {
    "id": 4,
    "category": "skeleton",
    "question": "橈骨と尺骨の位置関係として正しいものは？",
    "choices": ["橈骨は親指側、尺骨は小指側", "橈骨は小指側、尺骨は親指側", "どちらも中央にある", "左右で逆になる"],
    "answer": 0
  },
  {
    "id": 5,
    "category": "skeleton",
    "question": "寛骨を構成する骨はどれ？",
    "choices": ["腸骨・坐骨・恥骨", "腸骨・脛骨・恥骨", "坐骨・脛骨・腓骨", "腸骨・尾骨・恥骨"],
    "answer": 0
  },
  {
    "id": 6,
    "category": "skeleton",
    "question": "脊柱の中で最も可動性が高い部分は？",
    "choices": ["頸椎", "胸椎", "腰椎", "仙椎"],
    "answer": 0
  },
  {
    "id": 7,
    "category": "skeleton",
    "question": "胸郭を構成する骨はどれ？",
    "choices": ["肋骨・胸骨・胸椎", "肋骨・胸骨・腰椎", "肩甲骨・胸骨・肋骨", "胸椎・鎖骨・肋骨"],
    "answer": 0
  },
  {
    "id": 8,
    "category": "skeleton",
    "question": "膝関節を構成する骨の組み合わせとして正しいものは？",
    "choices": ["大腿骨・脛骨・膝蓋骨", "大腿骨・腓骨・膝蓋骨", "腓骨・脛骨・膝蓋骨", "大腿骨・距骨・膝蓋骨"],
    "answer": 0
  },
  {
    "id": 9,
    "category": "skeleton",
    "question": "足根骨に含まれないものはどれ？",
    "choices": ["舟状骨", "立方骨", "月状骨", "距骨"],
    "answer": 2
  },
  {
    "id": 10,
    "category": "skeleton",
    "question": "肩甲骨に存在する構造はどれ？",
    "choices": ["肩峰", "大腿骨頭", "上腕骨滑車", "脛骨粗面"],
    "answer": 0
  },
  {
    "id": 11,
    "category": "skeleton",
    "question": "肘関節で橈骨と関節する上腕骨の部位は？",
    "choices": ["小頭（上腕骨小頭）", "滑車", "大結節", "外側上顆"],
    "answer": 0
  },
  {
    "id": 12,
    "category": "skeleton",
    "question": "寛骨臼に当てはまる骨の構造はどれ？",
    "choices": ["大腿骨頭がはまるくぼみ", "上腕骨頭がはまるくぼみ", "膝蓋骨が収まる溝", "距骨がはまるくぼみ"],
    "answer": 0
  },
  {
    "id": 13,
    "category": "skeleton",
    "question": "鎖骨の外側端が関節するのはどれ？",
    "choices": ["肩峰", "胸骨柄", "肩甲骨下角", "肩甲骨関節窩"],
    "answer": 0
  },
  {
    "id": 14,
    "category": "skeleton",
    "question": "第1頸椎（環椎）の特徴として正しいものは？",
    "choices": ["椎体がない", "棘突起が非常に長い", "横突孔がない", "肋骨が付着する"],
    "answer": 0
  },
  {
    "id": 15,
    "category": "skeleton",
    "question": "大腿骨に存在する構造はどれ？",
    "choices": ["大転子", "烏口突起", "舟状骨", "上腕骨滑車"],
    "answer": 0
  },
  {
    "id": 16,
    "category": "skeleton",
    "question": "肩甲骨の前面にある窪みとして正しいものは？",
    "choices": ["肩甲下窩", "棘上窩", "棘下窩", "肩峰窩"],
    "answer": 0
  },
  {
    "id": 17,
    "category": "skeleton",
    "question": "手根骨に含まれる骨として正しいものは？",
    "choices": ["有頭骨", "距骨", "立方骨", "舟状骨（足の）"],
    "answer": 0
  },
  {
    "id": 18,
    "category": "skeleton",
    "question": "腓骨の位置として正しいものは？",
    "choices": ["下腿の外側に位置する", "下腿の内側に位置する", "大腿の内側に位置する", "大腿の外側に位置する"],
    "answer": 0
  },
  {
    "id": 19,
    "category": "skeleton",
    "question": "胸骨の構成として正しいものは？",
    "choices": ["胸骨柄・胸骨体・剣状突起", "胸骨柄・胸骨窩・剣状突起", "胸骨頭・胸骨体・剣状突起", "胸骨柄・胸骨臼・胸骨体"],
    "answer": 0
  },
  {
    "id": 20,
    "category": "skeleton",
    "question": "脊柱の生理的弯曲で、成人で前弯している部位はどれ？",
    "choices": ["頸椎と腰椎", "胸椎と仙椎", "胸椎のみ", "腰椎のみ"],
    "answer": 0
  },
  {
    "id": 21,
    "category": "upper",
    "question": "上腕二頭筋長頭の起始部はどこ？",
    "choices": ["烏口突起", "関節上結節", "肩甲棘", "小結節"],
    "answer": 1
  },
  {
    "id": 22,
    "category": "upper",
    "question": "上腕三頭筋のうち、肩関節をまたぐ頭はどれ？",
    "choices": ["外側頭", "内側頭", "長頭", "短頭"],
    "answer": 2
  },
  {
    "id": 23,
    "category": "upper",
    "question": "上腕筋の主な作用として正しいものは？",
    "choices": ["肘関節屈曲", "肘関節伸展", "肩関節内旋", "肩関節外転"],
    "answer": 0
  },
  {
    "id": 24,
    "category": "upper",
    "question": "三角筋中部線維の主な作用は？",
    "choices": ["肩関節屈曲", "肩関節外転", "肩関節内旋", "肩関節伸展"],
    "answer": 1
  },
  {
    "id": 25,
    "category": "upper",
    "question": "棘上筋の主な作用は？",
    "choices": ["肩関節外転の開始", "肩関節伸展", "肩関節屈曲", "肩関節内旋"],
    "answer": 0
  },
  {
    "id": 26,
    "category": "upper",
    "question": "棘下筋の主な作用は？",
    "choices": ["肩関節外旋", "肩関節内旋", "肩関節外転", "肩関節水平内転"],
    "answer": 0
  },
  {
    "id": 27,
    "category": "upper",
    "question": "小円筋の主な作用として正しいものは？",
    "choices": ["肩関節外旋", "肩関節内旋", "肩関節外転", "肩関節屈曲"],
    "answer": 0
  },
  {
    "id": 28,
    "category": "upper",
    "question": "広背筋の作用として正しいものは？",
    "choices": ["肩関節内転・伸展・内旋", "肩関節外転", "肘関節屈曲", "肩関節水平伸展のみ"],
    "answer": 0
  },
  {
    "id": 29,
    "category": "upper",
    "question": "大胸筋の作用として正しいものは？",
    "choices": ["肩関節水平内転", "肩関節外転", "肘関節屈曲", "肩甲骨挙上"],
    "answer": 0
  },
  {
    "id": 30,
    "category": "upper",
    "question": "前鋸筋の主な作用は？",
    "choices": ["肩甲骨の上方回旋", "肩甲骨の下制", "肩甲骨の内転", "肩甲骨の挙上"],
    "answer": 0
  },
  {
    "id": 31,
    "category": "upper",
    "question": "肩甲下筋の主な作用として正しいものは？",
    "choices": ["肩関節内旋", "肩関節外旋", "肩関節外転", "肩関節伸展"],
    "answer": 0
  },
  {
    "id": 32,
    "category": "upper",
    "question": "烏口腕筋の作用として正しいものは？",
    "choices": ["肩関節屈曲・内転", "肘関節屈曲", "肩関節外旋", "肩関節伸展"],
    "answer": 0
  },
  {
    "id": 33,
    "category": "upper",
    "question": "腕橈骨筋の主な作用として正しいものは？",
    "choices": ["肘関節屈曲", "前腕回内", "前腕回外", "肩関節伸展"],
    "answer": 0
  },
  {
    "id": 34,
    "category": "upper",
    "question": "円回内筋の主な作用は？",
    "choices": ["前腕回内", "前腕回外", "肘関節伸展", "肩関節外転"],
    "answer": 0
  },
  {
    "id": 35,
    "category": "upper",
    "question": "回外筋の主な作用は？",
    "choices": ["前腕回外", "前腕回内", "肘関節屈曲", "肩関節水平内転"],
    "answer": 0
  },
  {
    "id": 36,
    "category": "upper",
    "question": "橈側手根屈筋の作用として正しいものは？",
    "choices": ["手関節屈曲・橈屈", "手関節伸展", "手関節尺屈", "肘関節伸展"],
    "answer": 0
  },
  {
    "id": 37,
    "category": "upper",
    "question": "尺側手根屈筋の作用は？",
    "choices": ["手関節屈曲・尺屈", "手関節屈曲・橈屈", "手関節伸展", "前腕回外"],
    "answer": 0
  },
  {
    "id": 38,
    "category": "upper",
    "question": "長橈側手根伸筋の主作用は？",
    "choices": ["手関節伸展・橈屈", "手関節屈曲・橈屈", "手関節屈曲・尺屈", "前腕回内"],
    "answer": 0
  },
  {
    "id": 39,
    "category": "upper",
    "question": "短橈側手根伸筋の作用として正しいものは？",
    "choices": ["手関節伸展", "手関節屈曲", "肩関節内旋", "肘関節屈曲"],
    "answer": 0
  },
  {
    "id": 40,
    "category": "upper",
    "question": "総指伸筋の主な作用は？",
    "choices": ["指の伸展", "指の屈曲", "手関節屈曲", "手関節尺屈"],
    "answer": 0
  },
  {
    "id": 41,
    "category": "upper",
    "question": "浅指屈筋の作用として正しいものは？",
    "choices": ["PIP関節の屈曲", "DIP関節の伸展", "手関節伸展", "母指外転"],
    "answer": 0
  },
  {
    "id": 42,
    "category": "upper",
    "question": "深指屈筋の主な作用は？",
    "choices": ["DIP関節の屈曲", "PIP関節屈曲", "MP関節伸展", "手関節回旋"],
    "answer": 0
  },
  {
    "id": 43,
    "category": "upper",
    "question": "長母指伸筋の主作用として正しいものは？",
    "choices": ["母指の伸展", "母指の屈曲", "母指の外転", "母指の内転"],
    "answer": 0
  },
  {
    "id": 44,
    "category": "upper",
    "question": "長母指屈筋の作用は？",
    "choices": ["母指IP関節の屈曲", "母指IP関節の伸展", "母指外転", "手関節伸展"],
    "answer": 0
  },
  {
    "id": 45,
    "category": "upper",
    "question": "小指外転筋の主な作用は？",
    "choices": ["小指の外転", "小指の屈曲", "小指の内転", "小指の伸展"],
    "answer": 0
  },
  {
    "id": 46,
    "category": "upper",
    "question": "虫様筋の主な作用として正しいものは？",
    "choices": ["MP関節屈曲・IP関節伸展", "MP関節伸展・IP関節屈曲", "母指の対立", "手関節回外"],
    "answer": 0
  },
  {
    "id": 47,
    "category": "upper",
    "question": "掌側骨間筋の主作用は？",
    "choices": ["指の内転", "指の外転", "MP関節伸展", "IP関節屈曲"],
    "answer": 0
  },
  {
    "id": 48,
    "category": "upper",
    "question": "背側骨間筋の主な作用は？",
    "choices": ["指の外転", "指の内転", "MP屈曲のみ", "IP伸展のみ"],
    "answer": 0
  },
  {
    "id": 49,
    "category": "upper",
    "question": "肩甲骨挙上に関与する筋は？",
    "choices": ["肩甲挙筋", "大円筋", "前鋸筋", "棘下筋"],
    "answer": 0
  },
  {
    "id": 50,
    "category": "upper",
    "question": "肩甲骨を下制する筋として正しいものは？",
    "choices": ["広背筋", "肩甲挙筋", "大菱形筋", "小円筋"],
    "answer": 0
  },
  [
  {
    "id": 51,
    "question": "腹直筋の主な作用はどれか？",
    "options": ["体幹の屈曲", "体幹の伸展", "体幹の外旋", "体幹の外転"],
    "answer": "体幹の屈曲"
  },
  {
    "id": 52,
    "question": "外腹斜筋の作用として正しいのはどれか？",
    "options": ["体幹の内旋", "体幹の外旋", "体幹の伸展", "体幹の外転"],
    "answer": "体幹の外旋"
  },
  {
    "id": 53,
    "question": "内腹斜筋の作用として正しいのはどれか？",
    "options": ["体幹の内旋", "体幹の屈曲", "体幹の外旋", "体幹の外転"],
    "answer": "体幹の内旋"
  },
  {
    "id": 54,
    "question": "腹横筋の主な役割はどれか？",
    "options": ["腹圧の上昇", "脊柱の伸展", "肩甲骨の挙上", "骨盤の前傾"],
    "answer": "腹圧の上昇"
  },
  {
    "id": 55,
    "question": "脊柱起立筋の主な作用はどれか？",
    "options": ["脊柱の伸展", "脊柱の屈曲", "脊柱の回旋", "脊柱の外転"],
    "answer": "脊柱の伸展"
  },
  {
    "id": 56,
    "question": "多裂筋の作用として正しいのはどれか？",
    "options": ["脊柱の安定化", "肩甲骨の外転", "肋骨の挙上", "骨盤の外旋"],
    "answer": "脊柱の安定化"
  },
  {
    "id": 57,
    "question": "横隔膜の主な作用はどれか？",
    "options": ["吸気の補助", "呼気の補助", "体幹の回旋", "腹圧の低下"],
    "answer": "吸気の補助"
  },
  {
    "id": 58,
    "question": "肋間筋の主な役割はどれか？",
    "options": ["呼吸運動", "骨盤の傾斜", "肩甲骨の固定", "脊柱の回旋"],
    "answer": "呼吸運動"
  },
  {
    "id": 59,
    "question": "腰方形筋の作用はどれか？",
    "options": ["体幹の側屈", "体幹の伸展", "体幹の屈曲", "体幹の回旋"],
    "answer": "体幹の側屈"
  },
  {
    "id": 60,
    "question": "大臀筋の主な作用はどれか？",
    "options": ["股関節伸展", "股関節屈曲", "股関節内転", "股関節外旋"],
    "answer": "股関節伸展"
  },
  {
    "id": 61,
    "question": "中臀筋の主な作用はどれか？",
    "options": ["股関節外転", "股関節内転", "股関節伸展", "股関節屈曲"],
    "answer": "股関節外転"
  },
  {
    "id": 62,
    "question": "小臀筋の主な作用はどれか？",
    "options": ["股関節外転", "股関節伸展", "股関節内旋", "骨盤の前傾"],
    "answer": "股関節外転"
  },
  {
    "id": 63,
    "question": "腸腰筋の主な作用はどれか？",
    "options": ["股関節屈曲", "股関節伸展", "股関節内転", "股関節外旋"],
    "answer": "股関節屈曲"
  },
  {
    "id": 64,
    "question": "大腰筋はどの動作に最も関与するか？",
    "options": ["股関節屈曲", "股関節伸展", "膝関節屈曲", "体幹伸展"],
    "answer": "股関節屈曲"
  },
  {
    "id": 65,
    "question": "腹直筋の起始部はどこか？",
    "options": ["恥骨", "肋骨", "胸骨柄", "寛骨"],
    "answer": "恥骨"
  },
  {
    "id": 66,
    "question": "腹直筋の停止部はどこか？",
    "options": ["肋骨", "大腿骨", "肩甲骨", "胸椎"],
    "answer": "肋骨"
  },
  {
    "id": 67,
    "question": "外腹斜筋の起始部はどこか？",
    "options": ["下位肋骨", "胸骨", "鎖骨", "上腕骨"],
    "answer": "下位肋骨"
  },
  {
    "id": 68,
    "question": "内腹斜筋はどこに停止するか？",
    "options": ["肋骨・白線", "肩甲骨", "寛骨", "胸骨"],
    "answer": "肋骨・白線"
  },
  {
    "id": 69,
    "question": "腹横筋の起始部として正しいのはどれか？",
    "options": ["腰筋膜", "肋骨下部", "胸骨", "大腿骨"],
    "answer": "腰筋膜"
  },
  {
    "id": 70,
    "question": "脊柱起立筋はどの領域を走行するか？",
    "options": ["脊柱全体", "頸部のみ", "胸部のみ", "腰部のみ"],
    "answer": "脊柱全体"
  },
  {
    "id": 71,
    "question": "多裂筋の停止部はどこか？",
    "options": ["椎骨棘突起", "胸骨", "肋骨上部", "寛骨"],
    "answer": "椎骨棘突起"
  },
  {
    "id": 72,
    "question": "横隔膜はどの構造と連動して働くか？",
    "options": ["肺", "心臓", "脾臓", "膵臓"],
    "answer": "肺"
  },
  {
    "id": 73,
    "question": "腹圧を高めるために最も重要な筋はどれか？",
    "options": ["腹横筋", "大胸筋", "僧帽筋", "上腕二頭筋"],
    "answer": "腹横筋"
  },
  {
    "id": 74,
    "question": "大臀筋はどの動作で最も強く働くか？",
    "options": ["立ち上がり動作", "歩行のスイング", "背伸び", "握力動作"],
    "answer": "立ち上がり動作"
  },
  {
    "id": 75,
    "question": "中臀筋はどの動作で重要か？",
    "options": ["片脚立位の安定", "肩の外転", "呼吸", "肘の伸展"],
    "answer": "片脚立位の安定"
  },
  {
    "id": 76,
    "question": "腰方形筋はどの動作を助けるか？",
    "options": ["体幹側屈", "体幹伸展", "体幹回旋", "肩甲骨内転"],
    "answer": "体幹側屈"
  },
  {
    "id": 77,
    "question": "腸腰筋はどの姿勢で重要か？",
    "options": ["姿勢保持（立位）", "腕立て伏せ", "背筋運動", "懸垂"],
    "answer": "姿勢保持（立位）"
  },
  {
    "id": 78,
    "question": "体幹の回旋動作で主に働く筋はどれか？",
    "options": ["内腹斜筋・外腹斜筋", "大胸筋", "僧帽筋", "横隔膜"],
    "answer": "内腹斜筋・外腹斜筋"
  },
  {
    "id": 79,
    "question": "脊柱の安定性に最も貢献する筋はどれか？",
    "options": ["多裂筋", "上腕三頭筋", "広背筋", "三角筋"],
    "answer": "多裂筋"
  },
  {
    "id": 80,
    "question": "体幹屈曲を行う主動筋はどれか？",
    "options": ["腹直筋", "脊柱起立筋", "大臀筋", "中臀筋"],
    "answer": "腹直筋"
  },
  {
    "id": 81,
    "question": "母指球筋群に含まれる筋はどれか？",
    "options": ["短母指外転筋", "虫様筋", "背側骨間筋", "尺側手根屈筋"],
    "answer": "短母指外転筋"
  },
  {
    "id": 82,
    "question": "小指球筋群に含まれる筋はどれか？",
    "options": ["短小指屈筋", "短橈側手根伸筋", "長母指外転筋", "方形回内筋"],
    "answer": "短小指屈筋"
  },
  {
    "id": 83,
    "question": "虫様筋の主な作用はどれか？",
    "options": ["MP関節の屈曲とIP関節の伸展", "MP関節伸展", "IP関節屈曲", "母指の外転"],
    "answer": "MP関節の屈曲とIP関節の伸展"
  },
  {
    "id": 84,
    "question": "背側骨間筋の主な作用はどれか？",
    "options": ["指の外転", "指の内転", "母指の屈曲", "小指の伸展"],
    "answer": "指の外転"
  },
  {
    "id": 85,
    "question": "掌側骨間筋の作用はどれか？",
    "options": ["指の内転", "指の外転", "手関節の伸展", "母指外転"],
    "answer": "指の内転"
  },
  {
    "id": 86,
    "question": "短母指屈筋が属する筋群はどれか？",
    "options": ["母指球筋群", "小指球筋群", "骨間筋群", "前腕屈筋群"],
    "answer": "母指球筋群"
  },
  {
    "id": 87,
    "question": "長掌筋の停止部はどれか？",
    "options": ["手掌腱膜", "中手骨", "橈骨", "尺骨"],
    "answer": "手掌腱膜"
  },
  {
    "id": 88,
    "question": "短小指外転筋の作用はどれか？",
    "options": ["小指の外転", "小指の屈曲", "小指の伸展", "小指の内転"],
    "answer": "小指の外転"
  },
  {
    "id": 89,
    "question": "母指対立筋の作用はどれか？",
    "options": ["母指の対立", "母指の外転", "母指の伸展", "母指の回外"],
    "answer": "母指の対立"
  },
  {
    "id": 90,
    "question": "母指内転筋の機能として正しいのはどれか？",
    "options": ["母指の内転", "母指の屈曲", "母指の伸展", "母指の外転"],
    "answer": "母指の内転"
  },
  {
    "id": 91,
    "question": "浅指屈筋の作用はどれか？",
    "options": ["PIP関節の屈曲", "DIP関節の屈曲", "MP関節の伸展", "手関節の回外"],
    "answer": "PIP関節の屈曲"
  },
  {
    "id": 92,
    "question": "深指屈筋の主な作用はどれか？",
    "options": ["DIP関節の屈曲", "MP関節の伸展", "IP関節の外転", "橈屈"],
    "answer": "DIP関節の屈曲"
  },
  {
    "id": 93,
    "question": "長母指屈筋の作用はどれか？",
    "options": ["母指IP関節の屈曲", "母指の外転", "母指の伸展", "小指の内転"],
    "answer": "母指IP関節の屈曲"
  },
  {
    "id": 94,
    "question": "長母指外転筋の主な作用はどれか？",
    "options": ["母指の外転", "母指の伸展", "母指の屈曲", "小指外転"],
    "answer": "母指の外転"
  },
  {
    "id": 95,
    "question": "短母指伸筋の作用はどれか？",
    "options": ["母指MP関節の伸展", "母指の屈曲", "指の内転", "手関節屈曲"],
    "answer": "母指MP関節の伸展"
  },
  {
    "id": 96,
    "question": "小指対立筋の主な働きはどれか？",
    "options": ["小指の対立", "小指伸展", "小指屈曲", "小指内転"],
    "answer": "小指の対立"
  },
  {
    "id": 97,
    "question": "手内筋の特徴として正しいのはどれか？",
    "options": ["細かい指の動きを担う", "肘関節の屈曲を担う", "手関節の回内を行う", "前腕の回外を行う"],
    "answer": "細かい指の動きを担う"
  },
  {
    "id": 98,
    "question": "背側骨間筋は何個あるか？",
    "options": ["4つ", "3つ", "5つ", "1つ"],
    "answer": "4つ"
  },
  {
    "id": 99,
    "question": "掌側骨間筋は何個あるか？",
    "options": ["3つ", "4つ", "5つ", "1つ"],
    "answer": "3つ"
  },
  {
    "id": 100,
    "question": "母指球筋群が障害されるとどうなる？",
    "options": ["細かいつまみ動作が困難になる", "肘が伸びなくなる", "肩が挙がらない", "膝が動かない"],
    "answer": "細かいつまみ動作が困難になる"
  },
  {
    "id": 101,
    "question": "前脛骨筋の主な作用はどれか？",
    "options": ["足関節背屈・内反", "足関節底屈", "外反", "膝屈曲"],
    "answer": "足関節背屈・内反"
  },
  {
    "id": 102,
    "question": "腓腹筋の主な作用はどれか？",
    "options": ["足関節底屈", "足関節背屈", "内反", "股関節屈曲"],
    "answer": "足関節底屈"
  },
  {
    "id": 103,
    "question": "ヒラメ筋の作用として正しいものは？",
    "options": ["足関節底屈", "足関節外反", "膝関節伸展", "MP関節屈曲"],
    "answer": "足関節底屈"
  },
  {
    "id": 104,
    "question": "後脛骨筋の主な作用はどれか？",
    "options": ["足関節底屈・内反", "足関節背屈", "外反", "膝屈曲"],
    "answer": "足関節底屈・内反"
  },
  {
    "id": 105,
    "question": "長指屈筋の作用として正しいのは？",
    "options": ["足趾の屈曲", "足趾の伸展", "外反", "肩の屈曲"],
    "answer": "足趾の屈曲"
  },
  {
    "id": 106,
    "question": "長母趾屈筋の主な作用はどれか？",
    "options": ["母趾の屈曲", "母趾の外転", "足関節背屈", "母趾外旋"],
    "answer": "母趾の屈曲"
  },
  {
    "id": 107,
    "question": "長指伸筋の主な作用はどれか？",
    "options": ["足趾の伸展", "足関節底屈", "母趾内転", "膝屈曲"],
    "answer": "足趾の伸展"
  },
  {
    "id": 108,
    "question": "長母趾伸筋の作用として正しいのはどれか？",
    "options": ["母趾伸展", "母趾屈曲", "足関節底屈", "母趾外転"],
    "answer": "母趾伸展"
  },
  {
    "id": 109,
    "question": "腓骨筋（長腓骨筋・短腓骨筋）の主な作用はどれか？",
    "options": ["足関節外反", "足関節内反", "母趾屈曲", "足趾伸展"],
    "answer": "足関節外反"
  },
  {
    "id": 110,
    "question": "足底筋の特徴として正しいものはどれか？",
    "options": ["個人差が大きく欠損していることもある", "非常に強い筋力を持つ", "股関節に作用する", "前腕の回内に関与"],
    "answer": "個人差が大きく欠損していることもある"
  },
  {
    "id": 111,
    "question": "母趾外転筋の作用はどれか？",
    "options": ["母趾外転", "母趾屈曲", "踵の内反", "足趾伸展"],
    "answer": "母趾外転"
  },
  {
    "id": 112,
    "question": "短母趾屈筋の作用として正しいのは？",
    "options": ["母趾屈曲", "母趾外転", "足関節背屈", "膝伸展"],
    "answer": "母趾屈曲"
  },
  {
    "id": 113,
    "question": "小趾外転筋の主な作用はどれか？",
    "options": ["小趾外転", "小趾屈曲", "小趾伸展", "母趾の対立"],
    "answer": "小趾外転"
  },
  {
    "id": 114,
    "question": "足底方形筋の役割として正しいのはどれか？",
    "options": ["長指屈筋の引く方向を調整する", "足趾の伸展を行う", "足関節外反", "母趾内転"],
    "answer": "長指屈筋の引く方向を調整する"
  },
  {
    "id": 115,
    "question": "短指屈筋の作用として正しいのは？",
    "options": ["PIP関節の屈曲", "DIP関節屈曲", "外反", "内転"],
    "answer": "PIP関節の屈曲"
  },
  {
    "id": 116,
    "question": "足背の筋「短母趾伸筋」の作用はどれか？",
    "options": ["母趾伸展", "母趾屈曲", "外反", "底屈"],
    "answer": "母趾伸展"
  },
  {
    "id": 117,
    "question": "足背の筋「短指伸筋」の作用はどれか？",
    "options": ["足趾伸展", "足趾屈曲", "母趾外転", "足関節内反"],
    "answer": "足趾伸展"
  },
  {
    "id": 118,
    "question": "足内在筋の役割として正しいのはどれか？",
    "options": ["足の土踏まず保持", "足関節背屈", "外反の制御", "膝関節の安定"],
    "answer": "足の土踏まず保持"
  },
  {
    "id": 119,
    "question": "足の骨間筋（背側・底側）の主な作用は？",
    "options": ["足趾の内転・外転", "足の背屈", "足の底屈", "足趾伸展"],
    "answer": "足趾の内転・外転"
  },
  {
    "id": 120,
    "question": "ヒラメ筋が障害されると最も困る動作はどれか？",
    "options": ["つま先立ち", "肩の挙上", "ひじ伸展", "指の屈曲"],
    "answer": "つま先立ち"
  }
]
